DSAlgos/LinkedList.py
DSAlgos/Queue.py
DSAlgos/Search.py
DSAlgos/Sorting.py
DSAlgos/Stack.py
DSAlgos/__init__.py
DSAlgos-0.1.dist-info/LICENSE.txt
DSAlgos-0.1.dist-info/METADATA
DSAlgos-0.1.dist-info/WHEEL
DSAlgos-0.1.dist-info/top_level.txt
DSAlgos-0.1.dist-info/RECORD
