Metadata-Version: 2.1
Name: DSAlgos
Version: 0.1
Summary: Library for basic algorithms
Home-page: https://github.com/harshit-ladia/Algorithms
Author: DSA
Author-email: niketbanetha@gmail.com
License: MIT
Download-URL: https://github.com/harshit-ladia/Algorithms/archive/v_01.tar.gz
Keywords: STACK,SORTING,SEARCHING,DSA
Platform: UNKNOWN
Classifier: Development Status :: 3 - Alpha
Classifier: Intended Audience :: Developers
Classifier: Topic :: Software Development :: Build Tools
Classifier: License :: OSI Approved :: MIT License
Classifier: Programming Language :: Python :: 3
Classifier: Programming Language :: Python :: 3.4
Classifier: Programming Language :: Python :: 3.5
Classifier: Programming Language :: Python :: 3.6
Requires-Dist: validators
Requires-Dist: beautifulsoup4
